myfunctions.py
setup.py
Risk_lib_jt393.egg-info/PKG-INFO
Risk_lib_jt393.egg-info/SOURCES.txt
Risk_lib_jt393.egg-info/dependency_links.txt
Risk_lib_jt393.egg-info/top_level.txt