Metadata-Version: 2.1
Name: Risk-lib-jt393
Version: 0.1
Summary: Risk management
Author: Jingyu Tan
Author-email: t1169242950@gmail.com
